mopack/__init__.py
mopack/app_version.py
mopack/archive.py
mopack/arguments.py
mopack/base_options.py
mopack/commands.py
mopack/config.py
mopack/driver.py
mopack/environment.py
mopack/exceptions.py
mopack/expression.py
mopack/freezedried.py
mopack/glob.py
mopack/iterutils.py
mopack/log.py
mopack/metadata.py
mopack/objutils.py
mopack/options.py
mopack/package_defaults.py
mopack/path.py
mopack/pkg_config.py
mopack/placeholder.py
mopack/platforms.py
mopack/shell.py
mopack/types.py
mopack/yaml_tools.py
mopack/builders/__init__.py
mopack/builders/bfg9000.py
mopack/builders/cmake.py
mopack/builders/custom.py
mopack/builders/none.py
mopack/defaults/Qt5.yml
mopack/defaults/boost.yml
mopack/defaults/gl.yml
mopack/defaults/glu.yml
mopack/defaults/glut.yml
mopack/defaults/pthread.yml
mopack/defaults/zlib.yml
mopack/origins/__init__.py
mopack/origins/apt.py
mopack/origins/conan.py
mopack/origins/sdist.py
mopack/origins/system.py
mopack/usage/__init__.py
mopack/usage/path_system.py
mopack/usage/pkg_config.py
mopack/usage/submodules.py
mopack-0.1.0.dist-info/LICENSE
mopack-0.1.0.dist-info/METADATA
mopack-0.1.0.dist-info/WHEEL
mopack-0.1.0.dist-info/entry_points.txt
mopack-0.1.0.dist-info/top_level.txt
mopack-0.1.0.dist-info/RECORD
