Metadata-Version: 2.1
Name: mopack
Version: 0.1.0
Summary: A multiple-origin package manager
Home-page: https://github.com/jimporter/mopack
Author: Jim Porter
Author-email: itsjimporter@gmail.com
License: BSD-3-Clause
Keywords: package manager
Platform: UNKNOWN
Classifier: Development Status :: 3 - Alpha
Classifier: Intended Audience :: Developers
Classifier: Topic :: Software Development :: Build Tools
Classifier: License :: OSI Approved :: BSD License
Classifier: Programming Language :: Python :: 3
Classifier: Programming Language :: Python :: 3.6
Classifier: Programming Language :: Python :: 3.7
Classifier: Programming Language :: Python :: 3.8
Classifier: Programming Language :: Python :: 3.9
Classifier: Programming Language :: Python :: 3.10
Classifier: Programming Language :: Python :: 3.11
Provides-Extra: dev
Provides-Extra: test
